requirements.txt
setup.py
django_dev_urls/__init__.py
django_dev_urls/urls.py
django_dev_urls.egg-info/PKG-INFO
django_dev_urls.egg-info/SOURCES.txt
django_dev_urls.egg-info/dependency_links.txt
django_dev_urls.egg-info/requires.txt
django_dev_urls.egg-info/top_level.txt