Metadata-Version: 2.1
Name: django-dev-urls
Version: 2020.7.1
Summary: Django development urlpatterns
Home-page: https://github.com/andrewp-as-is/django-dev-urls.py
License: Unlicense
Keywords: Django dev urls
Platform: UNKNOWN
Classifier: Framework :: Django
Classifier: License :: Public Domain
Classifier: Operating System :: OS Independent
Classifier: Programming Language :: Python :: 3
